{
  "categories": [
    {
      "category_en": "sabahiyatsy",
      "category_ar": "صباحيات",
      "total": 3059,
      "recently_added": 0
    },
    {
      "category_en": "masaiyatsy",
      "category_ar": "مسائيات",
      "total": 1016,
      "recently_added": 0
    },
    {
      "category_en": "cimaasy",
      "category_ar": "يوم الجمعة",
      "total": 2257,
      "recently_added": 0
    },
    {
      "category_en": "islamiyatsy",
      "category_ar": "اسلاميات",
      "total": 6012,
      "recently_added": 0
    },
    {
      "category_en": "muhibbisuriyasy",
      "category_ar": "مُحِبين سوريا",
      "total": 2175,
      "recently_added": 0
    },
    {
      "category_en": "falastinsy",
      "category_ar": "فلسطينيات",
      "total": 1306,
      "recently_added": 0
    },
    {
      "category_en": "hawatersy",
      "category_ar": "خواطر وعِبر",
      "total": 4106,
      "recently_added": 0
    },
    {
      "category_en": "hobsy",
      "category_ar": "حب وغرام",
      "total": 5286,
      "recently_added": 0
    },
    {
      "category_en": "hayatsy",
      "category_ar": "عن الحياة",
      "total": 6704,
      "recently_added": 0
    },
    {
      "category_en": "analoumsy",
      "category_ar": "عن الأم",
      "total": 1635,
      "recently_added": 0
    },
    {
      "category_en": "analabsy",
      "category_ar": "عن الأب",
      "total": 994,
      "recently_added": 0
    },
    {
      "category_en": "analakhtsy",
      "category_ar": "عن الأخت",
      "total": 647,
      "recently_added": 0
    },
    {
      "category_en": "analakhsy",
      "category_ar": "عن الأخ",
      "total": 263,
      "recently_added": 0
    },
    {
      "category_en": "alwalidayinsy",
      "category_ar": "عن الوالدين",
      "total": 998,
      "recently_added": 0
    },
    {
      "category_en": "asdiqaasy",
      "category_ar": "عن الأصدقاء",
      "total": 1274,
      "recently_added": 0
    },
    {
      "category_en": "kibriyaaimraasy",
      "category_ar": "كبرياء أُنثى",
      "total": 1764,
      "recently_added": 0
    },
    {
      "category_en": "kibriyaarajulsy",
      "category_ar": "كبرياء رجُل",
      "total": 295,
      "recently_added": 0
    },
    {
      "category_en": "eidmiladsy",
      "category_ar": "عيد ميلاد",
      "total": 1310,
      "recently_added": 0
    },

    {
      "category_en": "takharrujsy",
      "category_ar": "عن التخرج",
      "total": 663,
      "recently_added": 0
    },
    {
      "category_en": "shiirsy",
      "category_ar": "شِعر عربي",
      "total": 4372,
      "recently_added": 0
    },
    {
      "category_en": "riadhsy",
      "category_ar": "رياضة",
      "total": 1859,
      "recently_added": 0
    },
    {
      "category_en": "zawajsy",
      "category_ar": "خطوبة وزواج",
      "total": 924,
      "recently_added": 0
    },
    {
      "category_en": "animisy",
      "category_ar": "أنِمي",
      "total": 1303,
      "recently_added": 0
    },
    {
      "category_en": "mimzatsy",
      "category_ar": "ميمزات",
      "total": 1362,
      "recently_added": 0
    },

    {
      "category_en": "mutheksy",
      "category_ar": "مُضحك",
      "total": 1612,
      "recently_added": 0
    }
  ]
}
